Gueye_Ndour/__init__.py
Gueye_Ndour/bisextiles.py
Gueye_Ndour/multiplication.py
Gueye_Ndour-1.0.0.dist-info/METADATA
Gueye_Ndour-1.0.0.dist-info/WHEEL
Gueye_Ndour-1.0.0.dist-info/top_level.txt
Gueye_Ndour-1.0.0.dist-info/RECORD
