Metadata-Version: 2.1
Name: Gueye-Ndour
Version: 1.0.0
Summary: distribution example
Home-page: https://github.com/interface22/python/Gueye_Ndour_package
Author: supinfo teams
Author-email: mgfree01@gmail.com
License: GPLv3
Keywords: distribution pypi setup.py
Platform: UNKNOWN
Classifier: Development Status :: 3 - Alpha
Classifier: Intended Audience :: Developers
Classifier: Programming Language :: Python :: 3.4
Classifier: Programming Language :: Python :: 3.5
Classifier: Programming Language :: Python :: 3.6
Classifier: Topic :: Software Development :: Testing
Classifier: License :: OSI Approved :: GNU General Public License v3 (GPLv3)
Requires-Python: >=3.4
Requires-Dist: voluptuous
